setup.cfg
setup.py
loadig/__init__.py
loadig/bar.py
loadig/utilities.py
loadig.egg-info/PKG-INFO
loadig.egg-info/SOURCES.txt
loadig.egg-info/dependency_links.txt
loadig.egg-info/top_level.txt