Metadata-Version: 1.1
Name: loadig
Version: 0.5.2
Summary: A minimal progress bar.
Home-page: https://github.com/busfahren/loadig
Author: Willi Raschkowski
Author-email: willi.raschkowski@student.hpi.de
License: UNKNOWN
Download-URL: https://github.com/busfahren/loadig/tarball/0.5.2
Keywords: bar,loading,progress,logging,loadig
Platform: UNKNOWN
